express_server/__init__.py
express_server/express.py
express_server/__pycache__/__init__.cpython-311.pyc
express_server/__pycache__/express.cpython-311.pyc
express_server/lib/http_server.py
express_server/lib/__pycache__/http_server.cpython-311.pyc
express_server/lib/constants/__init__.py
express_server/lib/constants/__pycache__/__init__.cpython-311.pyc
express_server/lib/constants/__pycache__/files.cpython-311.pyc
express_server/lib/manage_user_routes/manage_routes.py
express_server/lib/manage_user_routes/user_defind_route.py
express_server/lib/manage_user_routes/__pycache__/manage_routes.cpython-311.pyc
express_server/lib/manage_user_routes/__pycache__/user_defind_route.cpython-311.pyc
express_server/lib/route_handler/handle_paths.py
express_server/lib/route_handler/handle_routes.py
express_server/lib/route_handler/__pycache__/handle_paths.cpython-311.pyc
express_server/lib/route_handler/__pycache__/handle_routes.cpython-311.pyc
express_server/lib/routes/RequestRoute.py
express_server/lib/routes/ResponseRoute.py
express_server/lib/routes/__pycache__/RequestRoute.cpython-311.pyc
express_server/lib/routes/__pycache__/ResponseRoute.cpython-311.pyc
express_server/lib/utils/attributes.py
express_server/lib/utils/express.py
express_server/lib/utils/file_oprations.py
express_server/lib/utils/pages.py
express_server/lib/utils/paths.py
express_server/lib/utils/styles.py
express_server/lib/utils/__pycache__/attributes.cpython-311.pyc
express_server/lib/utils/__pycache__/express.cpython-311.pyc
express_server/lib/utils/__pycache__/file_oprations.cpython-311.pyc
express_server/lib/utils/__pycache__/files_helper.cpython-311.pyc
express_server/lib/utils/__pycache__/pages.cpython-311.pyc
express_server/lib/utils/__pycache__/paths.cpython-311.pyc
express_server/lib/utils/__pycache__/styles.cpython-311.pyc
express_server-0.0.6.dist-info/LICENSE
express_server-0.0.6.dist-info/METADATA
express_server-0.0.6.dist-info/WHEEL
express_server-0.0.6.dist-info/top_level.txt
express_server-0.0.6.dist-info/RECORD
