Metadata-Version: 2.1
Name: express-server
Version: 0.0.6
Summary: Express-Server is a lightweight and fast web server for Python, inspired by the simplicity of Express.js.
Home-page: https://example.com/
Author: Avinash Tare
Author-email: avinashtare.work@gmail.com
License: (The MIT License)
Project-URL: Documentation, https://example.com/
Project-URL: Source, https://github.com/avinashtare/express-server-python
Keywords: express,python-express,express-python,express-server,server-express
Classifier: Development Status :: 3 - Alpha
Classifier: Programming Language :: Python :: 3
Classifier: Topic :: Internet :: WWW/HTTP :: Dynamic Content :: CGI Tools/Libraries
Classifier: Topic :: Software Development :: Libraries
Classifier: License :: OSI Approved :: MIT License
Requires-Python: >=3.1
License-File: LICENSE
